phantomfetch/__init__.py
phantomfetch/cache.py
phantomfetch/captcha.py
phantomfetch/engines/__init__.py
phantomfetch/engines/base.py
phantomfetch/engines/browser/__init__.py
phantomfetch/engines/browser/actions.py
phantomfetch/engines/browser/cdp.py
phantomfetch/engines/curl.py
phantomfetch/fetch.py
phantomfetch/pool.py
phantomfetch/telemetry.py
phantomfetch/tools/selector_builder.py
phantomfetch/types.py
phantomfetch-0.3.1.dist-info/WHEEL
phantomfetch-0.3.1.dist-info/entry_points.txt
phantomfetch-0.3.1.dist-info/METADATA
phantomfetch-0.3.1.dist-info/RECORD
