Metadata-Version: 2.3
Name: phantomfetch
Version: 0.3.1
Summary: High-performance agentic web scraping library combining curl-cffi speed with Playwright browser capabilities
Keywords: web-scraping,playwright,curl-cffi,async,browser-automation,http-client,agentic,anti-detection
Author: CosmicBull
Author-email: CosmicBull <cosmicbull@example.com>
License: MIT
Classifier: Development Status :: 3 - Alpha
Classifier: Intended Audience :: Developers
Classifier: License :: OSI Approved :: MIT License
Classifier: Programming Language :: Python :: 3
Classifier: Programming Language :: Python :: 3.13
Classifier: Topic :: Internet :: WWW/HTTP
Classifier: Topic :: Software Development :: Libraries :: Python Modules
Classifier: Framework :: AsyncIO
Requires-Dist: curl-cffi>=0.13.0
Requires-Dist: msgspec>=0.20.0
Requires-Dist: rebrowser-playwright>=1.52.0
Requires-Dist: undetected-playwright>=0.3.0
Requires-Dist: rusticsoup>=0.3.0
Requires-Dist: httpx>=0.27.0
Requires-Dist: opentelemetry-api>=1.38.0
Requires-Dist: opentelemetry-sdk>=1.38.0
Requires-Dist: loguru>=0.7.3
Requires-Dist: beautifulsoup4>=4.14.3
Requires-Python: >=3.13
Project-URL: Homepage, https://github.com/iristech-systems/PhantomFetch
Project-URL: Documentation, https://github.com/iristech-systems/PhantomFetch#readme
Project-URL: Repository, https://github.com/iristech-systems/PhantomFetch
Project-URL: Issues, https://github.com/iristech-systems/PhantomFetch/issues
Project-URL: Changelog, https://github.com/iristech-systems/PhantomFetch/blob/main/CHANGELOG.md
